smartenv.py
smartenv-1.0.1.dist-info/top_level.txt
smartenv-1.0.1.dist-info/METADATA
smartenv-1.0.1.dist-info/DESCRIPTION.rst
smartenv-1.0.1.dist-info/metadata.json
smartenv-1.0.1.dist-info/WHEEL
smartenv-1.0.1.dist-info/RECORD
